merrymake/__init__.py
merrymake/contenttype.py
merrymake/envelope.py
merrymake/environment.py
merrymake/imerrymake.py
merrymake/merrymake.py
merrymake/nullmerrymake.py
merrymake/replypayload.py
merrymake/streamhelper.py
merrymake/valuemapper.py
merrymake-6.0.0.dist-info/METADATA
merrymake-6.0.0.dist-info/WHEEL
merrymake-6.0.0.dist-info/RECORD
