Metadata-Version: 2.1
Name: merrymake
Version: 6.0.0
Summary: Service library for the Merrymake platform
Author: Nicolaj Græsholt
Author-email: ng@merrymake.eu
Requires-Python: >=3.11.2,<4.0.0
Classifier: Programming Language :: Python :: 3
Classifier: Programming Language :: Python :: 3.12
Requires-Dist: requests (==2.31.0)
